sigma_dataflow_custom/__init__.py
sigma_dataflow_custom/dofn.py
sigma_dataflow_custom/transform.py
sigma_dataflow_custom/utils.py
sigma_dataflow_custom-0.0.2.dist-info/METADATA
sigma_dataflow_custom-0.0.2.dist-info/WHEEL
sigma_dataflow_custom-0.0.2.dist-info/top_level.txt
sigma_dataflow_custom-0.0.2.dist-info/RECORD
